{
  "generatedAt": "2025-08-21T22:08:14.896Z",
  "args": [
    "--concurrency",
    "8",
    "--debug",
    "--report-all"
  ],
  "options": {
    "concurrency": 8,
    "porcelainMode": false,
    "noAutofix": false,
    "debugMode": true,
    "skipTsc": false
  },
  "timing": {
    "autofixMs": 3,
    "perFileMs": 6,
    "repoMs": 5893,
    "totalMs": 5901,
    "eslintBatchMs": 5790,
    "repoBreakdown": {
      "jscpdMs": 1432,
      "knipMs": 3384,
      "tscMs": 3835
    }
  },
  "reviewMode": "Full Project Scan",
  "filesAnalyzed": 18,
  "results": [
    {
      "filePath": "c:\\Users\\Jonny\\Code\\shopify-shipping\\components\\ActionStatus.tsx",
      "relPath": "components\\ActionStatus.tsx",
      "fileType": "components",
      "size": {
        "lines": 23,
        "limit": 150,
        "status": "PASS"
      },
      "comments": {
        "count": 0,
        "status": "PASS"
      },
      "react": {
        "hasReactImport": false,
        "hasUseCallback": false,
        "hasUseMemo": false,
        "hasUseEffect": false,
        "hasHooks": true,
        "issues": []
      },
      "consoleErrors": {
        "violations": [],
        "count": 0,
        "status": "PASS"
      },
      "eslint": {
        "errors": [],
        "warnings": []
      },
      "typescript": {
        "totalFunctions": 1,
        "missingReturnTypes": 0,
        "hasExplicitTypes": true,
        "status": "PASS",
        "details": []
      },
      "fallbackData": {
        "violations": [],
        "count": 0,
        "status": "PASS"
      },
      "timing": {
        "linesMs": 0,
        "commentsMs": 1,
        "reactMs": 0,
        "consoleMs": 0,
        "eslintMs": 0,
        "typescriptMs": 0,
        "fallbackMs": 1
      },
      "typescriptCompiler": {
        "errorCount": 0,
        "errors": [],
        "status": "PASS"
      },
      "deadCode": {
        "unusedExports": 0,
        "unusedTypes": 0,
        "unusedEnumMembers": 0,
        "unusedClassMembers": 0,
        "unlistedDependencies": 0,
        "unresolvedImports": 0,
        "unresolvedImportSpecifiers": [],
        "unlistedDependencyModules": [],
        "status": "PASS",
        "recommendations": []
      },
      "duplicates": {
        "count": 0,
        "segments": [],
        "status": "PASS",
        "recommendations": []
      }
    },
    {
      "filePath": "c:\\Users\\Jonny\\Code\\shopify-shipping\\components\\ConfirmLiveModal.tsx",
      "relPath": "components\\ConfirmLiveModal.tsx",
      "fileType": "components",
      "size": {
        "lines": 62,
        "limit": 150,
        "status": "PASS"
      },
      "comments": {
        "count": 0,
        "status": "PASS"
      },
      "react": {
        "hasReactImport": false,
        "hasUseCallback": false,
        "hasUseMemo": false,
        "hasUseEffect": true,
        "hasHooks": true,
        "issues": []
      },
      "consoleErrors": {
        "violations": [],
        "count": 0,
        "status": "PASS"
      },
      "eslint": {
        "errors": [],
        "warnings": []
      },
      "typescript": {
        "totalFunctions": 1,
        "missingReturnTypes": 0,
        "hasExplicitTypes": true,
        "status": "PASS",
        "details": []
      },
      "fallbackData": {
        "violations": [],
        "count": 0,
        "status": "PASS"
      },
      "timing": {
        "linesMs": 0,
        "commentsMs": 0,
        "reactMs": 0,
        "consoleMs": 0,
        "eslintMs": 0,
        "typescriptMs": 1,
        "fallbackMs": 0
      },
      "typescriptCompiler": {
        "errorCount": 0,
        "errors": [],
        "status": "PASS"
      },
      "deadCode": {
        "unusedExports": 0,
        "unusedTypes": 0,
        "unusedEnumMembers": 0,
        "unusedClassMembers": 0,
        "unlistedDependencies": 0,
        "unresolvedImports": 0,
        "unresolvedImportSpecifiers": [],
        "unlistedDependencyModules": [],
        "status": "PASS",
        "recommendations": []
      },
      "duplicates": {
        "count": 0,
        "segments": [],
        "status": "PASS",
        "recommendations": []
      }
    },
    {
      "filePath": "c:\\Users\\Jonny\\Code\\shopify-shipping\\components\\DeployControls.tsx",
      "relPath": "components\\DeployControls.tsx",
      "fileType": "components",
      "size": {
        "lines": 116,
        "limit": 150,
        "status": "PASS"
      },
      "comments": {
        "count": 0,
        "status": "PASS"
      },
      "react": {
        "hasReactImport": false,
        "hasUseCallback": true,
        "hasUseMemo": false,
        "hasUseEffect": false,
        "hasHooks": true,
        "issues": []
      },
      "consoleErrors": {
        "violations": [],
        "count": 0,
        "status": "PASS"
      },
      "eslint": {
        "errors": [],
        "warnings": []
      },
      "typescript": {
        "totalFunctions": 2,
        "missingReturnTypes": 0,
        "hasExplicitTypes": true,
        "status": "PASS",
        "details": []
      },
      "fallbackData": {
        "violations": [],
        "count": 0,
        "status": "PASS"
      },
      "timing": {
        "linesMs": 0,
        "commentsMs": 0,
        "reactMs": 0,
        "consoleMs": 0,
        "eslintMs": 0,
        "typescriptMs": 0,
        "fallbackMs": 0
      },
      "typescriptCompiler": {
        "errorCount": 0,
        "errors": [],
        "status": "PASS"
      },
      "deadCode": {
        "unusedExports": 0,
        "unusedTypes": 0,
        "unusedEnumMembers": 0,
        "unusedClassMembers": 0,
        "unlistedDependencies": 0,
        "unresolvedImports": 0,
        "unresolvedImportSpecifiers": [],
        "unlistedDependencyModules": [],
        "status": "PASS",
        "recommendations": []
      },
      "duplicates": {
        "count": 0,
        "segments": [],
        "status": "PASS",
        "recommendations": []
      }
    },
    {
      "filePath": "c:\\Users\\Jonny\\Code\\shopify-shipping\\components\\DeployProgressList.tsx",
      "relPath": "components\\DeployProgressList.tsx",
      "fileType": "components",
      "size": {
        "lines": 146,
        "limit": 150,
        "status": "PASS"
      },
      "comments": {
        "count": 0,
        "status": "PASS"
      },
      "react": {
        "hasReactImport": false,
        "hasUseCallback": false,
        "hasUseMemo": true,
        "hasUseEffect": false,
        "hasHooks": true,
        "issues": []
      },
      "consoleErrors": {
        "violations": [],
        "count": 0,
        "status": "PASS"
      },
      "eslint": {
        "errors": [],
        "warnings": []
      },
      "typescript": {
        "totalFunctions": 4,
        "missingReturnTypes": 0,
        "hasExplicitTypes": true,
        "status": "PASS",
        "details": []
      },
      "fallbackData": {
        "violations": [],
        "count": 0,
        "status": "PASS"
      },
      "timing": {
        "linesMs": 0,
        "commentsMs": 0,
        "reactMs": 0,
        "consoleMs": 0,
        "eslintMs": 0,
        "typescriptMs": 1,
        "fallbackMs": 0
      },
      "typescriptCompiler": {
        "errorCount": 0,
        "errors": [],
        "status": "PASS"
      },
      "deadCode": {
        "unusedExports": 0,
        "unusedTypes": 0,
        "unusedEnumMembers": 0,
        "unusedClassMembers": 0,
        "unlistedDependencies": 0,
        "unresolvedImports": 0,
        "unresolvedImportSpecifiers": [],
        "unlistedDependencyModules": [],
        "status": "PASS",
        "recommendations": []
      },
      "duplicates": {
        "count": 0,
        "segments": [],
        "status": "PASS",
        "recommendations": []
      }
    },
    {
      "filePath": "c:\\Users\\Jonny\\Code\\shopify-shipping\\components\\SummaryCard.tsx",
      "relPath": "components\\SummaryCard.tsx",
      "fileType": "components",
      "size": {
        "lines": 76,
        "limit": 150,
        "status": "PASS"
      },
      "comments": {
        "count": 0,
        "status": "PASS"
      },
      "react": {
        "hasReactImport": false,
        "hasUseCallback": false,
        "hasUseMemo": false,
        "hasUseEffect": false,
        "hasHooks": true,
        "issues": []
      },
      "consoleErrors": {
        "violations": [],
        "count": 0,
        "status": "PASS"
      },
      "eslint": {
        "errors": [],
        "warnings": []
      },
      "typescript": {
        "totalFunctions": 2,
        "missingReturnTypes": 0,
        "hasExplicitTypes": true,
        "status": "PASS",
        "details": []
      },
      "fallbackData": {
        "violations": [],
        "count": 0,
        "status": "PASS"
      },
      "timing": {
        "linesMs": 0,
        "commentsMs": 0,
        "reactMs": 0,
        "consoleMs": 0,
        "eslintMs": 0,
        "typescriptMs": 0,
        "fallbackMs": 0
      },
      "typescriptCompiler": {
        "errorCount": 0,
        "errors": [],
        "status": "PASS"
      },
      "deadCode": {
        "unusedExports": 0,
        "unusedTypes": 0,
        "unusedEnumMembers": 0,
        "unusedClassMembers": 0,
        "unlistedDependencies": 0,
        "unresolvedImports": 0,
        "unresolvedImportSpecifiers": [],
        "unlistedDependencyModules": [],
        "status": "PASS",
        "recommendations": []
      },
      "duplicates": {
        "count": 0,
        "segments": [],
        "status": "PASS",
        "recommendations": []
      }
    },
    {
      "filePath": "c:\\Users\\Jonny\\Code\\shopify-shipping\\lib\\api\\rates.ts",
      "relPath": "lib\\api\\rates.ts",
      "fileType": "utils",
      "size": {
        "lines": 47,
        "limit": 50,
        "status": "PASS"
      },
      "comments": {
        "count": 0,
        "status": "PASS"
      },
      "react": {
        "hasReactImport": false,
        "hasUseCallback": false,
        "hasUseMemo": false,
        "hasUseEffect": false,
        "hasHooks": false,
        "issues": []
      },
      "consoleErrors": {
        "violations": [],
        "count": 0,
        "status": "PASS"
      },
      "eslint": {
        "errors": [],
        "warnings": []
      },
      "typescript": {
        "totalFunctions": 4,
        "missingReturnTypes": 0,
        "hasExplicitTypes": true,
        "status": "PASS",
        "details": []
      },
      "fallbackData": {
        "violations": [],
        "count": 0,
        "status": "PASS"
      },
      "timing": {
        "linesMs": 0,
        "commentsMs": 0,
        "reactMs": 0,
        "consoleMs": 0,
        "eslintMs": 0,
        "typescriptMs": 0,
        "fallbackMs": 0
      },
      "typescriptCompiler": {
        "errorCount": 0,
        "errors": [],
        "status": "PASS"
      },
      "deadCode": {
        "unusedExports": 0,
        "unusedTypes": 0,
        "unusedEnumMembers": 0,
        "unusedClassMembers": 0,
        "unlistedDependencies": 0,
        "unresolvedImports": 0,
        "unresolvedImportSpecifiers": [],
        "unlistedDependencyModules": [],
        "status": "PASS",
        "recommendations": []
      },
      "duplicates": {
        "count": 0,
        "segments": [],
        "status": "PASS",
        "recommendations": []
      }
    },
    {
      "filePath": "c:\\Users\\Jonny\\Code\\shopify-shipping\\lib\\db.ts",
      "relPath": "lib\\db.ts",
      "fileType": "utils",
      "size": {
        "lines": 10,
        "limit": 50,
        "status": "PASS"
      },
      "comments": {
        "count": 0,
        "status": "PASS"
      },
      "react": {
        "hasReactImport": false,
        "hasUseCallback": false,
        "hasUseMemo": false,
        "hasUseEffect": false,
        "hasHooks": false,
        "issues": []
      },
      "consoleErrors": {
        "violations": [],
        "count": 0,
        "status": "PASS"
      },
      "eslint": {
        "errors": [],
        "warnings": []
      },
      "typescript": {
        "totalFunctions": 0,
        "missingReturnTypes": 0,
        "hasExplicitTypes": true,
        "status": "PASS",
        "details": []
      },
      "fallbackData": {
        "violations": [],
        "count": 0,
        "status": "PASS"
      },
      "timing": {
        "linesMs": 0,
        "commentsMs": 0,
        "reactMs": 0,
        "consoleMs": 0,
        "eslintMs": 0,
        "typescriptMs": 0,
        "fallbackMs": 0
      },
      "typescriptCompiler": {
        "errorCount": 0,
        "errors": [],
        "status": "PASS"
      },
      "deadCode": {
        "unusedExports": 0,
        "unusedTypes": 0,
        "unusedEnumMembers": 0,
        "unusedClassMembers": 0,
        "unlistedDependencies": 0,
        "unresolvedImports": 0,
        "unresolvedImportSpecifiers": [],
        "unlistedDependencyModules": [],
        "status": "PASS",
        "recommendations": []
      },
      "duplicates": {
        "count": 0,
        "segments": [],
        "status": "PASS",
        "recommendations": []
      }
    },
    {
      "filePath": "c:\\Users\\Jonny\\Code\\shopify-shipping\\types\\api.ts",
      "relPath": "types\\api.ts",
      "fileType": "types",
      "size": {
        "lines": 58,
        "limit": 100,
        "status": "PASS"
      },
      "comments": {
        "count": 0,
        "status": "PASS"
      },
      "react": {
        "hasReactImport": false,
        "hasUseCallback": false,
        "hasUseMemo": false,
        "hasUseEffect": false,
        "hasHooks": false,
        "issues": []
      },
      "consoleErrors": {
        "violations": [],
        "count": 0,
        "status": "PASS"
      },
      "eslint": {
        "errors": [],
        "warnings": []
      },
      "typescript": {
        "totalFunctions": 0,
        "missingReturnTypes": 0,
        "hasExplicitTypes": true,
        "status": "PASS",
        "details": []
      },
      "fallbackData": {
        "violations": [],
        "count": 0,
        "status": "PASS"
      },
      "timing": {
        "linesMs": 0,
        "commentsMs": 0,
        "reactMs": 0,
        "consoleMs": 0,
        "eslintMs": 0,
        "typescriptMs": 0,
        "fallbackMs": 0
      },
      "typescriptCompiler": {
        "errorCount": 0,
        "errors": [],
        "status": "PASS"
      },
      "deadCode": {
        "unusedExports": 0,
        "unusedTypes": 0,
        "unusedEnumMembers": 0,
        "unusedClassMembers": 0,
        "unlistedDependencies": 0,
        "unresolvedImports": 0,
        "unresolvedImportSpecifiers": [],
        "unlistedDependencyModules": [],
        "status": "PASS",
        "recommendations": []
      },
      "duplicates": {
        "count": 0,
        "segments": [],
        "status": "PASS",
        "recommendations": []
      }
    },
    {
      "filePath": "c:\\Users\\Jonny\\Code\\shopify-shipping\\types\\css-modules.ts",
      "relPath": "types\\css-modules.ts",
      "fileType": "types",
      "size": {
        "lines": 2,
        "limit": 100,
        "status": "PASS"
      },
      "comments": {
        "count": 0,
        "status": "PASS"
      },
      "react": {
        "hasReactImport": false,
        "hasUseCallback": false,
        "hasUseMemo": false,
        "hasUseEffect": false,
        "hasHooks": false,
        "issues": []
      },
      "consoleErrors": {
        "violations": [],
        "count": 0,
        "status": "PASS"
      },
      "eslint": {
        "errors": [],
        "warnings": []
      },
      "typescript": {
        "totalFunctions": 0,
        "missingReturnTypes": 0,
        "hasExplicitTypes": true,
        "status": "PASS",
        "details": []
      },
      "fallbackData": {
        "violations": [],
        "count": 0,
        "status": "PASS"
      },
      "timing": {
        "linesMs": 0,
        "commentsMs": 0,
        "reactMs": 0,
        "consoleMs": 0,
        "eslintMs": 0,
        "typescriptMs": 0,
        "fallbackMs": 0
      },
      "typescriptCompiler": {
        "errorCount": 0,
        "errors": [],
        "status": "PASS"
      },
      "deadCode": {
        "unusedExports": 0,
        "unusedTypes": 0,
        "unusedEnumMembers": 0,
        "unusedClassMembers": 0,
        "unlistedDependencies": 0,
        "unresolvedImports": 0,
        "unresolvedImportSpecifiers": [],
        "unlistedDependencyModules": [],
        "status": "PASS",
        "recommendations": []
      },
      "duplicates": {
        "count": 0,
        "segments": [],
        "status": "PASS",
        "recommendations": []
      }
    },
    {
      "filePath": "c:\\Users\\Jonny\\Code\\shopify-shipping\\types\\deployment-summary.ts",
      "relPath": "types\\deployment-summary.ts",
      "fileType": "types",
      "size": {
        "lines": 12,
        "limit": 100,
        "status": "PASS"
      },
      "comments": {
        "count": 0,
        "status": "PASS"
      },
      "react": {
        "hasReactImport": false,
        "hasUseCallback": false,
        "hasUseMemo": false,
        "hasUseEffect": false,
        "hasHooks": false,
        "issues": []
      },
      "consoleErrors": {
        "violations": [],
        "count": 0,
        "status": "PASS"
      },
      "eslint": {
        "errors": [],
        "warnings": []
      },
      "typescript": {
        "totalFunctions": 0,
        "missingReturnTypes": 0,
        "hasExplicitTypes": true,
        "status": "PASS",
        "details": []
      },
      "fallbackData": {
        "violations": [],
        "count": 0,
        "status": "PASS"
      },
      "timing": {
        "linesMs": 0,
        "commentsMs": 0,
        "reactMs": 0,
        "consoleMs": 0,
        "eslintMs": 0,
        "typescriptMs": 0,
        "fallbackMs": 0
      },
      "typescriptCompiler": {
        "errorCount": 0,
        "errors": [],
        "status": "PASS"
      },
      "deadCode": {
        "unusedExports": 0,
        "unusedTypes": 0,
        "unusedEnumMembers": 0,
        "unusedClassMembers": 0,
        "unlistedDependencies": 0,
        "unresolvedImports": 0,
        "unresolvedImportSpecifiers": [],
        "unlistedDependencyModules": [],
        "status": "PASS",
        "recommendations": []
      },
      "duplicates": {
        "count": 0,
        "segments": [],
        "status": "PASS",
        "recommendations": []
      }
    },
    {
      "filePath": "c:\\Users\\Jonny\\Code\\shopify-shipping\\types\\multi-zone-types.ts",
      "relPath": "types\\multi-zone-types.ts",
      "fileType": "types",
      "size": {
        "lines": 45,
        "limit": 100,
        "status": "PASS"
      },
      "comments": {
        "count": 0,
        "status": "PASS"
      },
      "react": {
        "hasReactImport": false,
        "hasUseCallback": false,
        "hasUseMemo": false,
        "hasUseEffect": false,
        "hasHooks": false,
        "issues": []
      },
      "consoleErrors": {
        "violations": [],
        "count": 0,
        "status": "PASS"
      },
      "eslint": {
        "errors": [],
        "warnings": []
      },
      "typescript": {
        "totalFunctions": 0,
        "missingReturnTypes": 0,
        "hasExplicitTypes": true,
        "status": "PASS",
        "details": []
      },
      "fallbackData": {
        "violations": [],
        "count": 0,
        "status": "PASS"
      },
      "timing": {
        "linesMs": 0,
        "commentsMs": 0,
        "reactMs": 0,
        "consoleMs": 0,
        "eslintMs": 0,
        "typescriptMs": 0,
        "fallbackMs": 0
      },
      "typescriptCompiler": {
        "errorCount": 0,
        "errors": [],
        "status": "PASS"
      },
      "deadCode": {
        "unusedExports": 0,
        "unusedTypes": 0,
        "unusedEnumMembers": 0,
        "unusedClassMembers": 0,
        "unlistedDependencies": 0,
        "unresolvedImports": 0,
        "unresolvedImportSpecifiers": [],
        "unlistedDependencyModules": [],
        "status": "PASS",
        "recommendations": []
      },
      "duplicates": {
        "count": 0,
        "segments": [],
        "status": "PASS",
        "recommendations": []
      }
    },
    {
      "filePath": "c:\\Users\\Jonny\\Code\\shopify-shipping\\types\\rate-generation.ts",
      "relPath": "types\\rate-generation.ts",
      "fileType": "types",
      "size": {
        "lines": 74,
        "limit": 100,
        "status": "PASS"
      },
      "comments": {
        "count": 0,
        "status": "PASS"
      },
      "react": {
        "hasReactImport": false,
        "hasUseCallback": false,
        "hasUseMemo": false,
        "hasUseEffect": false,
        "hasHooks": false,
        "issues": []
      },
      "consoleErrors": {
        "violations": [],
        "count": 0,
        "status": "PASS"
      },
      "eslint": {
        "errors": [],
        "warnings": []
      },
      "typescript": {
        "totalFunctions": 2,
        "missingReturnTypes": 0,
        "hasExplicitTypes": true,
        "status": "PASS",
        "details": []
      },
      "fallbackData": {
        "violations": [],
        "count": 0,
        "status": "PASS"
      },
      "timing": {
        "linesMs": 0,
        "commentsMs": 0,
        "reactMs": 0,
        "consoleMs": 0,
        "eslintMs": 0,
        "typescriptMs": 1,
        "fallbackMs": 0
      },
      "typescriptCompiler": {
        "errorCount": 0,
        "errors": [],
        "status": "PASS"
      },
      "deadCode": {
        "unusedExports": 0,
        "unusedTypes": 0,
        "unusedEnumMembers": 0,
        "unusedClassMembers": 0,
        "unlistedDependencies": 0,
        "unresolvedImports": 0,
        "unresolvedImportSpecifiers": [],
        "unlistedDependencyModules": [],
        "status": "PASS",
        "recommendations": []
      },
      "duplicates": {
        "count": 0,
        "segments": [],
        "status": "PASS",
        "recommendations": []
      }
    },
    {
      "filePath": "c:\\Users\\Jonny\\Code\\shopify-shipping\\types\\rates.ts",
      "relPath": "types\\rates.ts",
      "fileType": "types",
      "size": {
        "lines": 46,
        "limit": 100,
        "status": "PASS"
      },
      "comments": {
        "count": 0,
        "status": "PASS"
      },
      "react": {
        "hasReactImport": false,
        "hasUseCallback": false,
        "hasUseMemo": false,
        "hasUseEffect": false,
        "hasHooks": false,
        "issues": []
      },
      "consoleErrors": {
        "violations": [],
        "count": 0,
        "status": "PASS"
      },
      "eslint": {
        "errors": [],
        "warnings": []
      },
      "typescript": {
        "totalFunctions": 0,
        "missingReturnTypes": 0,
        "hasExplicitTypes": true,
        "status": "PASS",
        "details": []
      },
      "fallbackData": {
        "violations": [],
        "count": 0,
        "status": "PASS"
      },
      "timing": {
        "linesMs": 0,
        "commentsMs": 0,
        "reactMs": 0,
        "consoleMs": 0,
        "eslintMs": 0,
        "typescriptMs": 0,
        "fallbackMs": 0
      },
      "typescriptCompiler": {
        "errorCount": 0,
        "errors": [],
        "status": "PASS"
      },
      "deadCode": {
        "unusedExports": 0,
        "unusedTypes": 0,
        "unusedEnumMembers": 0,
        "unusedClassMembers": 0,
        "unlistedDependencies": 0,
        "unresolvedImports": 0,
        "unresolvedImportSpecifiers": [],
        "unlistedDependencyModules": [],
        "status": "PASS",
        "recommendations": []
      },
      "duplicates": {
        "count": 0,
        "segments": [],
        "status": "PASS",
        "recommendations": []
      }
    },
    {
      "filePath": "c:\\Users\\Jonny\\Code\\shopify-shipping\\types\\shopify-core.ts",
      "relPath": "types\\shopify-core.ts",
      "fileType": "types",
      "size": {
        "lines": 38,
        "limit": 100,
        "status": "PASS"
      },
      "comments": {
        "count": 0,
        "status": "PASS"
      },
      "react": {
        "hasReactImport": false,
        "hasUseCallback": false,
        "hasUseMemo": false,
        "hasUseEffect": false,
        "hasHooks": false,
        "issues": []
      },
      "consoleErrors": {
        "violations": [],
        "count": 0,
        "status": "PASS"
      },
      "eslint": {
        "errors": [],
        "warnings": []
      },
      "typescript": {
        "totalFunctions": 0,
        "missingReturnTypes": 0,
        "hasExplicitTypes": true,
        "status": "PASS",
        "details": []
      },
      "fallbackData": {
        "violations": [],
        "count": 0,
        "status": "PASS"
      },
      "timing": {
        "linesMs": 0,
        "commentsMs": 0,
        "reactMs": 0,
        "consoleMs": 0,
        "eslintMs": 0,
        "typescriptMs": 0,
        "fallbackMs": 0
      },
      "typescriptCompiler": {
        "errorCount": 0,
        "errors": [],
        "status": "PASS"
      },
      "deadCode": {
        "unusedExports": 0,
        "unusedTypes": 0,
        "unusedEnumMembers": 0,
        "unusedClassMembers": 0,
        "unlistedDependencies": 0,
        "unresolvedImports": 0,
        "unresolvedImportSpecifiers": [],
        "unlistedDependencyModules": [],
        "status": "PASS",
        "recommendations": []
      },
      "duplicates": {
        "count": 0,
        "segments": [],
        "status": "PASS",
        "recommendations": []
      }
    },
    {
      "filePath": "c:\\Users\\Jonny\\Code\\shopify-shipping\\types\\shopify-inputs.ts",
      "relPath": "types\\shopify-inputs.ts",
      "fileType": "types",
      "size": {
        "lines": 51,
        "limit": 100,
        "status": "PASS"
      },
      "comments": {
        "count": 0,
        "status": "PASS"
      },
      "react": {
        "hasReactImport": false,
        "hasUseCallback": false,
        "hasUseMemo": false,
        "hasUseEffect": false,
        "hasHooks": false,
        "issues": []
      },
      "consoleErrors": {
        "violations": [],
        "count": 0,
        "status": "PASS"
      },
      "eslint": {
        "errors": [],
        "warnings": []
      },
      "typescript": {
        "totalFunctions": 0,
        "missingReturnTypes": 0,
        "hasExplicitTypes": true,
        "status": "PASS",
        "details": []
      },
      "fallbackData": {
        "violations": [],
        "count": 0,
        "status": "PASS"
      },
      "timing": {
        "linesMs": 0,
        "commentsMs": 0,
        "reactMs": 0,
        "consoleMs": 0,
        "eslintMs": 0,
        "typescriptMs": 0,
        "fallbackMs": 0
      },
      "typescriptCompiler": {
        "errorCount": 0,
        "errors": [],
        "status": "PASS"
      },
      "deadCode": {
        "unusedExports": 0,
        "unusedTypes": 0,
        "unusedEnumMembers": 0,
        "unusedClassMembers": 0,
        "unlistedDependencies": 0,
        "unresolvedImports": 0,
        "unresolvedImportSpecifiers": [],
        "unlistedDependencyModules": [],
        "status": "PASS",
        "recommendations": []
      },
      "duplicates": {
        "count": 0,
        "segments": [],
        "status": "PASS",
        "recommendations": []
      }
    },
    {
      "filePath": "c:\\Users\\Jonny\\Code\\shopify-shipping\\types\\shopify-mutation-responses.ts",
      "relPath": "types\\shopify-mutation-responses.ts",
      "fileType": "types",
      "size": {
        "lines": 21,
        "limit": 100,
        "status": "PASS"
      },
      "comments": {
        "count": 0,
        "status": "PASS"
      },
      "react": {
        "hasReactImport": false,
        "hasUseCallback": false,
        "hasUseMemo": false,
        "hasUseEffect": false,
        "hasHooks": false,
        "issues": []
      },
      "consoleErrors": {
        "violations": [],
        "count": 0,
        "status": "PASS"
      },
      "eslint": {
        "errors": [],
        "warnings": []
      },
      "typescript": {
        "totalFunctions": 0,
        "missingReturnTypes": 0,
        "hasExplicitTypes": true,
        "status": "PASS",
        "details": []
      },
      "fallbackData": {
        "violations": [],
        "count": 0,
        "status": "PASS"
      },
      "timing": {
        "linesMs": 0,
        "commentsMs": 0,
        "reactMs": 0,
        "consoleMs": 0,
        "eslintMs": 0,
        "typescriptMs": 0,
        "fallbackMs": 0
      },
      "typescriptCompiler": {
        "errorCount": 0,
        "errors": [],
        "status": "PASS"
      },
      "deadCode": {
        "unusedExports": 0,
        "unusedTypes": 0,
        "unusedEnumMembers": 0,
        "unusedClassMembers": 0,
        "unlistedDependencies": 0,
        "unresolvedImports": 0,
        "unresolvedImportSpecifiers": [],
        "unlistedDependencyModules": [],
        "status": "PASS",
        "recommendations": []
      },
      "duplicates": {
        "count": 0,
        "segments": [],
        "status": "PASS",
        "recommendations": []
      }
    },
    {
      "filePath": "c:\\Users\\Jonny\\Code\\shopify-shipping\\types\\shopify-query-responses.ts",
      "relPath": "types\\shopify-query-responses.ts",
      "fileType": "types",
      "size": {
        "lines": 57,
        "limit": 100,
        "status": "PASS"
      },
      "comments": {
        "count": 0,
        "status": "PASS"
      },
      "react": {
        "hasReactImport": false,
        "hasUseCallback": false,
        "hasUseMemo": false,
        "hasUseEffect": false,
        "hasHooks": false,
        "issues": []
      },
      "consoleErrors": {
        "violations": [],
        "count": 0,
        "status": "PASS"
      },
      "eslint": {
        "errors": [],
        "warnings": []
      },
      "typescript": {
        "totalFunctions": 0,
        "missingReturnTypes": 0,
        "hasExplicitTypes": true,
        "status": "PASS",
        "details": []
      },
      "fallbackData": {
        "violations": [],
        "count": 0,
        "status": "PASS"
      },
      "timing": {
        "linesMs": 0,
        "commentsMs": 0,
        "reactMs": 0,
        "consoleMs": 0,
        "eslintMs": 0,
        "typescriptMs": 0,
        "fallbackMs": 0
      },
      "typescriptCompiler": {
        "errorCount": 0,
        "errors": [],
        "status": "PASS"
      },
      "deadCode": {
        "unusedExports": 0,
        "unusedTypes": 0,
        "unusedEnumMembers": 0,
        "unusedClassMembers": 0,
        "unlistedDependencies": 0,
        "unresolvedImports": 0,
        "unresolvedImportSpecifiers": [],
        "unlistedDependencyModules": [],
        "status": "PASS",
        "recommendations": []
      },
      "duplicates": {
        "count": 0,
        "segments": [],
        "status": "PASS",
        "recommendations": []
      }
    },
    {
      "filePath": "c:\\Users\\Jonny\\Code\\shopify-shipping\\types\\zone-rate-types.ts",
      "relPath": "types\\zone-rate-types.ts",
      "fileType": "types",
      "size": {
        "lines": 23,
        "limit": 100,
        "status": "PASS"
      },
      "comments": {
        "count": 0,
        "status": "PASS"
      },
      "react": {
        "hasReactImport": false,
        "hasUseCallback": false,
        "hasUseMemo": false,
        "hasUseEffect": false,
        "hasHooks": false,
        "issues": []
      },
      "consoleErrors": {
        "violations": [],
        "count": 0,
        "status": "PASS"
      },
      "eslint": {
        "errors": [],
        "warnings": []
      },
      "typescript": {
        "totalFunctions": 0,
        "missingReturnTypes": 0,
        "hasExplicitTypes": true,
        "status": "PASS",
        "details": []
      },
      "fallbackData": {
        "violations": [],
        "count": 0,
        "status": "PASS"
      },
      "timing": {
        "linesMs": 0,
        "commentsMs": 0,
        "reactMs": 0,
        "consoleMs": 0,
        "eslintMs": 0,
        "typescriptMs": 0,
        "fallbackMs": 0
      },
      "typescriptCompiler": {
        "errorCount": 0,
        "errors": [],
        "status": "PASS"
      },
      "deadCode": {
        "unusedExports": 0,
        "unusedTypes": 0,
        "unusedEnumMembers": 0,
        "unusedClassMembers": 0,
        "unlistedDependencies": 0,
        "unresolvedImports": 0,
        "unresolvedImportSpecifiers": [],
        "unlistedDependencyModules": [],
        "status": "PASS",
        "recommendations": []
      },
      "duplicates": {
        "count": 0,
        "segments": [],
        "status": "PASS",
        "recommendations": []
      }
    }
  ],
  "summary": {
    "status": "pass",
    "noViolations": true,
    "message": "No violations detected. No further action required."
  },
  "repo": {
    "knip": {
      "unusedFiles": 0,
      "unusedExports": 0,
      "unusedTypes": 0,
      "unusedEnumMembers": 0,
      "unusedClassMembers": 0,
      "unlistedDependencies": 0,
      "unresolvedImports": 0
    },
    "knipDetails": {
      "unresolvedImports": [],
      "unlistedDependencies": [],
      "unusedFiles": [],
      "unusedExports": []
    },
    "jscpd": {
      "groups": 0,
      "duplicatedLines": 0,
      "percentage": 0
    },
    "tsc": {
      "totalErrors": 0,
      "tsconfigPath": "c:\\Users\\Jonny\\Code\\shopify-shipping\\ai-subtree\\review\\tsconfig.review.json"
    }
  }
}
